mcparser.py
recipe_sraper_jksdfghkdsfhgkdfghlk-0.0.1.dist-info/licenses/LICENSE.txt
recipe_sraper_jksdfghkdsfhgkdfghlk-0.0.1.dist-info/METADATA
recipe_sraper_jksdfghkdsfhgkdfghlk-0.0.1.dist-info/WHEEL
recipe_sraper_jksdfghkdsfhgkdfghlk-0.0.1.dist-info/top_level.txt
recipe_sraper_jksdfghkdsfhgkdfghlk-0.0.1.dist-info/RECORD
